webthing/__init__.py
webthing/action.py
webthing/auth.py
webthing/containers.py
webthing/db.py
webthing/errors.py
webthing/event.py
webthing/handlers.py
webthing/middlewares.py
webthing/mixins.py
webthing/model.py
webthing/property.py
webthing/rule_engine.py
webthing/server.py
webthing/thing.py
webthing/utils.py
webthing/value.py
aiowebthing-0.1.25.dist-info/LICENSE.txt
aiowebthing-0.1.25.dist-info/METADATA
aiowebthing-0.1.25.dist-info/WHEEL
aiowebthing-0.1.25.dist-info/top_level.txt
aiowebthing-0.1.25.dist-info/RECORD
