Metadata-Version: 2.1
Name: aiowebthing
Version: 0.1.25
Summary: High performance implementation of Web of Things
Home-page: https://github.com/hidaris/aiowebthing
Author: hidaris
Author-email: zuocool@gmail.com
License: MPL-2.0
Project-URL: Source, https://github.com/hidaris/aiowebthing
Project-URL: Tracker, https://github.com/hidaris/aiowebthing/issues
Keywords: async mozilla iot web-of-things webthings
Platform: UNKNOWN
Classifier: Development Status :: 4 - Beta
Classifier: Intended Audience :: Developers
Classifier: License :: OSI Approved :: Mozilla Public License 2.0 (MPL 2.0)
Classifier: Programming Language :: Python :: 3.6
Classifier: Programming Language :: Python :: 3.7
Classifier: Programming Language :: Python :: 3.8
Requires-Python: >=3.6, <4
Requires-Dist: ifaddr (>=0.1.0)
Requires-Dist: pyee (>=7.0.0)
Requires-Dist: jsonschema (>=3.2.0)
Requires-Dist: zeroconf (>=0.27.0)
Requires-Dist: ujson
Requires-Dist: pyjwt
Requires-Dist: httpx (==0.13.*)
Requires-Dist: starlette (==0.13.*)
Requires-Dist: uvicorn (==0.11.*)
Requires-Dist: tortoise-orm (==0.16.*)
